imputer/__init__.py
imputer/cli.py
imputer/core.py
imputer/feature_categories.json
imputer/models/dae_model_high.h5
imputer/models/dae_model_low.h5
microbiome_imputer-0.1.1.dist-info/METADATA
microbiome_imputer-0.1.1.dist-info/WHEEL
microbiome_imputer-0.1.1.dist-info/entry_points.txt
microbiome_imputer-0.1.1.dist-info/top_level.txt
microbiome_imputer-0.1.1.dist-info/RECORD
